CHANGELOG.md
MANIFEST.in
README.rst
setup.cfg
setup.py
src/gulpio2/__init__.py
src/gulpio2/__version__.py
src/gulpio2/adapters.py
src/gulpio2/fileio.py
src/gulpio2/sanity_utils.py
src/gulpio2/template.jinja
src/gulpio2/utils.py
src/gulpio2.egg-info/PKG-INFO
src/gulpio2.egg-info/SOURCES.txt
src/gulpio2.egg-info/dependency_links.txt
src/gulpio2.egg-info/requires.txt
src/gulpio2.egg-info/top_level.txt
src/gulpio2/scripts/gulp2_20bn_csv_jpeg
src/gulpio2/scripts/gulp2_20bn_csv_webm
src/gulpio2/scripts/gulp2_20bn_json_videos
src/gulpio2/scripts/gulp2_activitynet
src/gulpio2/scripts/gulp2_image_folder
src/gulpio2/scripts/gulp2_image_list
src/gulpio2/scripts/gulp2_kinetics
src/gulpio2/scripts/gulp2_register_adapter
src/gulpio2/scripts/gulp2_sanity_check
src/gulpio2/scripts/gulp2_video_folder