Metadata-Version: 2.1
Name: gulpio2
Version: 0.0.4
Summary: Binary storage format for deep learning on videos.
Home-page: https://github.com/willprice/GulpIO2
Author: Eren Golge (eren.golge@twentybn.com), Raghav Goyal (raghav.goyal@twentybn.com), Susanne Westphal (susanne.westphal@twentybn.com), Heuna Kim (heuna.kim@twentybn.com), Guillaume Berger (guillaume.berger@twentybn.com), Joanna Materzyńska (joanna.materzynska@twentybn.com), Florian Letsch (florian.letsch@twentybn.com), Valentin Haenel (valentin.haenel@twentybn.com), Will Price (will.price94+dev@gmail.com), 
Author-email: will.price94+gulpio2@gmail.com
License: MIT
Platform: UNKNOWN
Classifier: License :: OSI Approved :: MIT License
Classifier: Programming Language :: Python
Classifier: Programming Language :: Python :: 3
Classifier: Programming Language :: Python :: 3.6
Classifier: Programming Language :: Python :: 3.7
Classifier: Programming Language :: Python :: 3.8
Classifier: Programming Language :: Python :: Implementation :: CPython
Requires-Python: >=3.6.0
